doc2markdown/__init__.py
doc2markdown/server.py
doc2markdown_mcp-0.1.0.dist-info/METADATA
doc2markdown_mcp-0.1.0.dist-info/WHEEL
doc2markdown_mcp-0.1.0.dist-info/entry_points.txt
doc2markdown_mcp-0.1.0.dist-info/RECORD
