Metadata-Version: 2.4
Name: doc2markdown-mcp
Version: 0.1.0
Summary: MCP server for converting documents to Markdown format
Project-URL: Homepage, https://github.com/yourusername/doc2markdown
Project-URL: Repository, https://github.com/yourusername/doc2markdown
Author: Jia Liu
License-Expression: MIT
Keywords: conversion,document,docx,markdown,mcp,pdf
Classifier: Development Status :: 4 - Beta
Classifier: Intended Audience :: Developers
Classifier: License :: OSI Approved :: MIT License
Classifier: Programming Language :: Python :: 3
Classifier: Programming Language :: Python :: 3.10
Classifier: Programming Language :: Python :: 3.11
Classifier: Programming Language :: Python :: 3.12
Requires-Python: >=3.10
Requires-Dist: markitdown[all]>=0.1.0
Requires-Dist: mcp>=1.0.0
